bin/hbtxt.py
habits_txt/__init__.py
habits_txt/builder.py
habits_txt/cli.py
habits_txt/config.py
habits_txt/date.py
habits_txt/defaults.py
habits_txt/directives.py
habits_txt/exceptions.py
habits_txt/journal.py
habits_txt/models.py
habits_txt/parser.py
habits_txt/records_query.py
habits_txt/style.py
habits_txt-1.1.1.dist-info/METADATA
habits_txt-1.1.1.dist-info/WHEEL
habits_txt-1.1.1.dist-info/entry_points.txt
habits_txt-1.1.1.dist-info/RECORD
