Metadata-Version: 2.1
Name: habits.txt
Version: 1.1.1
Summary: 
Author: estebanthi
Author-email: esteban.thilliez@gmail.com
Requires-Python: >=3.12,<3.13
Classifier: Programming Language :: Python :: 3
Classifier: Programming Language :: Python :: 3.12
Requires-Dist: click (>=8.1.7,<9.0.0)
Requires-Dist: croniter (>=2.0.5,<3.0.0)
Requires-Dist: dateparser (>=1.2.0,<2.0.0)
Requires-Dist: datetime-matcher (>=0.2.1,<0.3.0)
Requires-Dist: pandas (>=2.2.2,<3.0.0)
Requires-Dist: plotly (>=5.22.0,<6.0.0)
